README.rst
setup.py
pony_database_facade/__init__.py
pony_database_facade/loader.py
pony_database_facade.egg-info/PKG-INFO
pony_database_facade.egg-info/SOURCES.txt
pony_database_facade.egg-info/dependency_links.txt
pony_database_facade.egg-info/not-zip-safe
pony_database_facade.egg-info/requires.txt
pony_database_facade.egg-info/top_level.txt