Metadata-Version: 1.1
Name: pony-database-facade
Version: 2.0.1
Summary: PonyORM Database object Facade
Home-page: https://github.com/kyzima-spb/pony-database-facade
Author: Kirill Vercetti
Author-email: office@kyzima-spb.com
License: Apache-2.0
Platform: UNKNOWN
Classifier: Development Status :: 4 - Beta
Classifier: Operating System :: OS Independent
Classifier: Programming Language :: Python
